pymodaq_plugins_mockexamples/__init__.py
pymodaq_plugins_mockexamples/utils.py
pymodaq_plugins_mockexamples/daq_move_plugins/__init__.py
pymodaq_plugins_mockexamples/daq_move_plugins/daq_move_BSPiezoMirror.py
pymodaq_plugins_mockexamples/daq_move_plugins/daq_move_BSPowerMeter.py
pymodaq_plugins_mockexamples/daq_move_plugins/daq_move_Harmonics.py
pymodaq_plugins_mockexamples/daq_move_plugins/daq_move_MockBinary.py
pymodaq_plugins_mockexamples/daq_move_plugins/daq_move_MockCamera.py
pymodaq_plugins_mockexamples/daq_move_plugins/daq_move_MockComplexSignal.py
pymodaq_plugins_mockexamples/daq_move_plugins/daq_move_MockNamedAxes.py
pymodaq_plugins_mockexamples/daq_move_plugins/daq_move_MockRandom.py
pymodaq_plugins_mockexamples/daq_move_plugins/daq_move_Pinem.py
pymodaq_plugins_mockexamples/daq_viewer_plugins/__init__.py
pymodaq_plugins_mockexamples/daq_viewer_plugins/plugins_0D/__init__.py
pymodaq_plugins_mockexamples/daq_viewer_plugins/plugins_0D/daq_0Dviewer_BSPhotodiode.py
pymodaq_plugins_mockexamples/daq_viewer_plugins/plugins_0D/daq_0Dviewer_Harmonics.py
pymodaq_plugins_mockexamples/daq_viewer_plugins/plugins_0D/daq_0Dviewer_MockAdaptive.py
pymodaq_plugins_mockexamples/daq_viewer_plugins/plugins_0D/daq_0Dviewer_MockComplexSignal.py
pymodaq_plugins_mockexamples/daq_viewer_plugins/plugins_0D/daq_0Dviewer_MockRandom.py
pymodaq_plugins_mockexamples/daq_viewer_plugins/plugins_1D/__init__.py
pymodaq_plugins_mockexamples/daq_viewer_plugins/plugins_1D/daq_1Dviewer_Harmonics.py
pymodaq_plugins_mockexamples/daq_viewer_plugins/plugins_1D/daq_1Dviewer_MockRandom.py
pymodaq_plugins_mockexamples/daq_viewer_plugins/plugins_1D/daq_1Dviewer_Mock_spectro.py
pymodaq_plugins_mockexamples/daq_viewer_plugins/plugins_1D/daq_1Dviewer_Pinem.py
pymodaq_plugins_mockexamples/daq_viewer_plugins/plugins_1D/daq_1Dviewer_PinemAnalysis.py
pymodaq_plugins_mockexamples/daq_viewer_plugins/plugins_2D/__init__.py
pymodaq_plugins_mockexamples/daq_viewer_plugins/plugins_2D/daq_2Dviewer_BSCamera.py
pymodaq_plugins_mockexamples-5.0.8.dist-info/METADATA
pymodaq_plugins_mockexamples-5.0.8.dist-info/WHEEL
pymodaq_plugins_mockexamples-5.0.8.dist-info/entry_points.txt
pymodaq_plugins_mockexamples-5.0.8.dist-info/licenses/LICENSE
pymodaq_plugins_mockexamples-5.0.8.dist-info/RECORD
